CHANGES.rst
MANIFEST.in
README.rst
setup.py
signpic/__init__.py
signpic/sign.py
signpic/signature.jpg
signpic.egg-info/PKG-INFO
signpic.egg-info/SOURCES.txt
signpic.egg-info/dependency_links.txt
signpic.egg-info/entry_points.txt
signpic.egg-info/not-zip-safe
signpic.egg-info/requires.txt
signpic.egg-info/top_level.txt