Metadata-Version: 1.0
Name: signpic
Version: 0.1
Summary: Signpic inserts in yoru pictures a signature
Home-page: UNKNOWN
Author: Tarek Ziade
Author-email: tarek@ziade.org
License: UNKNOWN
Platform: UNKNOWN
Classifier: Programming Language :: Python
Classifier: Development Status :: 3 - Alpha
